{
    "SurahID": 64,
    "Name": "التغابن",
    "TotalNumberedVerses": 18,
    "TotalVerses": 19,
    "Ayahs": [
        {
            "AyahID": 0,
            "RawText": "بِسْمِ ٱللَّهِ ٱلرَّحْمَـٰنِ ٱلرَّحِيمِ",
            "SanitizedText": "بسم ٱلله ٱلرحمـٰن ٱلرحيم",
            "TotalWords": 4,
            "TotalGematricValue": 783,
            "Words": [
                "بسم",
                "ٱلله",
                "ٱلرحمـٰن",
                "ٱلرحيم"
            ],
            "GematricValues": [
                102,
                65,
                328,
                288
            ],
            "VerseType": "Unnumbered"
        },
        {
            "AyahID": 1,
            "RawText": "يُسَبِّحُ لِلَّهِ مَا فِى ٱلسَّمَـٰوَٰتِ وَمَا فِى ٱلْأَرْضِ ۖ لَهُ ٱلْمُلْكُ وَلَهُ ٱلْحَمْدُ ۖ وَهُوَ عَلَىٰ كُلِّ شَىْءٍ قَدِيرٌ",
            "SanitizedText": "يسبح لله ما في ٱلسمـٰوٰت وما في ٱلارض ۖ له ٱلملك وله ٱلحمد ۖ وهو عليٰ كل شيء قدير",
            "TotalWords": 19,
            "TotalGematricValue": 3059,
            "Words": [
                "يسبح",
                "لله",
                "ما",
                "في",
                "ٱلسمـٰوٰت",
                "وما",
                "في",
                "ٱلارض",
                "ۖ",
                "له",
                "ٱلملك",
                "وله",
                "ٱلحمد",
                "ۖ",
                "وهو",
                "عليٰ",
                "كل",
                "شيء",
                "قدير"
            ],
            "GematricValues": [
                80,
                65,
                41,
                90,
                536,
                47,
                90,
                1031,
                0,
                35,
                120,
                41,
                82,
                0,
                17,
                110,
                50,
                310,
                314
            ],
            "VerseType": "Numbered"
        },
        {
            "AyahID": 2,
            "RawText": "هُوَ ٱلَّذِى خَلَقَكُمْ فَمِنكُمْ كَافِرٌ وَمِنكُم مُّؤْمِنٌ ۚ وَٱللَّهُ بِمَا تَعْمَلُونَ بَصِيرٌ",
            "SanitizedText": "هو ٱلذي خلقكم فمنكم كافر ومنكم مؤمن ۚ وٱلله بما تعملون بصير",
            "TotalWords": 12,
            "TotalGematricValue": 3370,
            "Words": [
                "هو",
                "ٱلذي",
                "خلقكم",
                "فمنكم",
                "كافر",
                "ومنكم",
                "مؤمن",
                "ۚ",
                "وٱلله",
                "بما",
                "تعملون",
                "بصير"
            ],
            "GematricValues": [
                11,
                740,
                790,
                230,
                301,
                156,
                130,
                0,
                71,
                43,
                596,
                302
            ],
            "VerseType": "Numbered"
        },
        {
            "AyahID": 3,
            "RawText": "خَلَقَ ٱلسَّمَـٰوَٰتِ وَٱلْأَرْضَ بِٱلْحَقِّ وَصَوَّرَكُمْ فَأَحْسَنَ صُوَرَكُمْ ۖ وَإِلَيْهِ ٱلْمَصِيرُ",
            "SanitizedText": "خلق ٱلسمـٰوٰت وٱلارض بٱلحق وصوركم فاحسن صوركم ۖ واليه ٱلمصير",
            "TotalWords": 10,
            "TotalGematricValue": 3782,
            "Words": [
                "خلق",
                "ٱلسمـٰوٰت",
                "وٱلارض",
                "بٱلحق",
                "وصوركم",
                "فاحسن",
                "صوركم",
                "ۖ",
                "واليه",
                "ٱلمصير"
            ],
            "GematricValues": [
                730,
                536,
                1037,
                140,
                362,
                199,
                356,
                0,
                52,
                370
            ],
            "VerseType": "Numbered"
        },
        {
            "AyahID": 4,
            "RawText": "يَعْلَمُ مَا فِى ٱلسَّمَـٰوَٰتِ وَٱلْأَرْضِ وَيَعْلَمُ مَا تُسِرُّونَ وَمَا تُعْلِنُونَ ۚ وَٱللَّهُ عَلِيمٌۢ بِذَاتِ ٱلصُّدُورِ",
            "SanitizedText": "يعلم ما في ٱلسمـٰوٰت وٱلارض ويعلم ما تسرون وما تعلنون ۚ وٱلله عليمۢ بذات ٱلصدور",
            "TotalWords": 15,
            "TotalGematricValue": 5074,
            "Words": [
                "يعلم",
                "ما",
                "في",
                "ٱلسمـٰوٰت",
                "وٱلارض",
                "ويعلم",
                "ما",
                "تسرون",
                "وما",
                "تعلنون",
                "ۚ",
                "وٱلله",
                "عليمۢ",
                "بذات",
                "ٱلصدور"
            ],
            "GematricValues": [
                150,
                41,
                90,
                536,
                1037,
                156,
                41,
                716,
                47,
                606,
                0,
                71,
                150,
                1103,
                330
            ],
            "VerseType": "Numbered"
        },
        {
            "AyahID": 5,
            "RawText": "أَلَمْ يَأْتِكُمْ نَبَؤُا۟ ٱلَّذِينَ كَفَرُوا۟ مِن قَبْلُ فَذَاقُوا۟ وَبَالَ أَمْرِهِمْ وَلَهُمْ عَذَابٌ أَلِيمٌ",
            "SanitizedText": "الم ياتكم نبؤا۟ ٱلذين كفروا۟ من قبل فذاقوا۟ وبال امرهم ولهم عذاب اليم",
            "TotalWords": 13,
            "TotalGematricValue": 4062,
            "Words": [
                "الم",
                "ياتكم",
                "نبؤا۟",
                "ٱلذين",
                "كفروا۟",
                "من",
                "قبل",
                "فذاقوا۟",
                "وبال",
                "امرهم",
                "ولهم",
                "عذاب",
                "اليم"
            ],
            "GematricValues": [
                71,
                471,
                53,
                790,
                307,
                90,
                132,
                888,
                39,
                286,
                81,
                773,
                81
            ],
            "VerseType": "Numbered"
        },
        {
            "AyahID": 6,
            "RawText": "ذَٰلِكَ بِأَنَّهُۥ كَانَت تَّأْتِيهِمْ رُسُلُهُم بِٱلْبَيِّنَـٰتِ فَقَالُوٓا۟ أَبَشَرٌ يَهْدُونَنَا فَكَفَرُوا۟ وَتَوَلَّوا۟ ۚ وَّٱسْتَغْنَى ٱللَّهُ ۚ وَٱللَّهُ غَنِىٌّ حَمِيدٌ",
            "SanitizedText": "ذٰلك بانهۥ كانت تاتيهم رسلهم بٱلبينـٰت فقالوٓا۟ ابشر يهدوننا فكفروا۟ وتولوا۟ ۚ وٱستغني ٱلله ۚ وٱلله غني حميد",
            "TotalWords": 18,
            "TotalGematricValue": 7431,
            "Words": [
                "ذٰلك",
                "بانهۥ",
                "كانت",
                "تاتيهم",
                "رسلهم",
                "بٱلبينـٰت",
                "فقالوٓا۟",
                "ابشر",
                "يهدوننا",
                "فكفروا۟",
                "وتولوا۟",
                "ۚ",
                "وٱستغني",
                "ٱلله",
                "ۚ",
                "وٱلله",
                "غني",
                "حميد"
            ],
            "GematricValues": [
                750,
                58,
                471,
                856,
                335,
                494,
                218,
                503,
                126,
                387,
                449,
                0,
                1526,
                65,
                0,
                71,
                1060,
                62
            ],
            "VerseType": "Numbered"
        },
        {
            "AyahID": 7,
            "RawText": "زَعَمَ ٱلَّذِينَ كَفَرُوٓا۟ أَن لَّن يُبْعَثُوا۟ ۚ قُلْ بَلَىٰ وَرَبِّى لَتُبْعَثُنَّ ثُمَّ لَتُنَبَّؤُنَّ بِمَا عَمِلْتُمْ ۚ وَذَٰلِكَ عَلَى ٱللَّهِ يَسِيرٌ",
            "SanitizedText": "زعم ٱلذين كفروٓا۟ ان لن يبعثوا۟ ۚ قل بليٰ وربي لتبعثن ثم لتنبؤن بما عملتم ۚ وذٰلك علي ٱلله يسير",
            "TotalWords": 20,
            "TotalGematricValue": 6282,
            "Words": [
                "زعم",
                "ٱلذين",
                "كفروٓا۟",
                "ان",
                "لن",
                "يبعثوا۟",
                "ۚ",
                "قل",
                "بليٰ",
                "وربي",
                "لتبعثن",
                "ثم",
                "لتنبؤن",
                "بما",
                "عملتم",
                "ۚ",
                "وذٰلك",
                "علي",
                "ٱلله",
                "يسير"
            ],
            "GematricValues": [
                117,
                790,
                307,
                51,
                80,
                589,
                0,
                130,
                42,
                218,
                1052,
                540,
                532,
                43,
                580,
                0,
                756,
                110,
                65,
                280
            ],
            "VerseType": "Numbered"
        },
        {
            "AyahID": 8,
            "RawText": "فَـَٔامِنُوا۟ بِٱللَّهِ وَرَسُولِهِۦ وَٱلنُّورِ ٱلَّذِىٓ أَنزَلْنَا ۚ وَٱللَّهُ بِمَا تَعْمَلُونَ خَبِيرٌ",
            "SanitizedText": "فـٔامنوا۟ بٱلله ورسولهۦ وٱلنور ٱلذيٓ انزلنا ۚ وٱلله بما تعملون خبير",
            "TotalWords": 11,
            "TotalGematricValue": 3245,
            "Words": [
                "فـٔامنوا۟",
                "بٱلله",
                "ورسولهۦ",
                "وٱلنور",
                "ٱلذيٓ",
                "انزلنا",
                "ۚ",
                "وٱلله",
                "بما",
                "تعملون",
                "خبير"
            ],
            "GematricValues": [
                178,
                67,
                307,
                292,
                740,
                139,
                0,
                71,
                43,
                596,
                812
            ],
            "VerseType": "Numbered"
        },
        {
            "AyahID": 9,
            "RawText": "يَوْمَ يَجْمَعُكُمْ لِيَوْمِ ٱلْجَمْعِ ۖ ذَٰلِكَ يَوْمُ ٱلتَّغَابُنِ ۗ وَمَن يُؤْمِنۢ بِٱللَّهِ وَيَعْمَلْ صَـٰلِحًا يُكَفِّرْ عَنْهُ سَيِّـَٔاتِهِۦ وَيُدْخِلْهُ جَنَّـٰتٍ تَجْرِى مِن تَحْتِهَا ٱلْأَنْهَـٰرُ خَـٰلِدِينَ فِيهَآ أَبَدًا ۚ ذَٰلِكَ ٱلْفَوْزُ ٱلْعَظِيمُ",
            "SanitizedText": "يوم يجمعكم ليوم ٱلجمع ۖ ذٰلك يوم ٱلتغابن ۗ ومن يؤمنۢ بٱلله ويعمل صـٰلحا يكفر عنه سيـٔاتهۦ ويدخله جنـٰت تجري من تحتها ٱلانهـٰر خـٰلدين فيهآ ابدا ۚ ذٰلك ٱلفوز ٱلعظيم",
            "TotalWords": 30,
            "TotalGematricValue": 9848,
            "Words": [
                "يوم",
                "يجمعكم",
                "ليوم",
                "ٱلجمع",
                "ۖ",
                "ذٰلك",
                "يوم",
                "ٱلتغابن",
                "ۗ",
                "ومن",
                "يؤمنۢ",
                "بٱلله",
                "ويعمل",
                "صـٰلحا",
                "يكفر",
                "عنه",
                "سيـٔاتهۦ",
                "ويدخله",
                "جنـٰت",
                "تجري",
                "من",
                "تحتها",
                "ٱلانهـٰر",
                "خـٰلدين",
                "فيهآ",
                "ابدا",
                "ۚ",
                "ذٰلك",
                "ٱلفوز",
                "ٱلعظيم"
            ],
            "GematricValues": [
                56,
                183,
                86,
                143,
                0,
                750,
                56,
                1483,
                0,
                96,
                100,
                67,
                156,
                129,
                310,
                125,
                476,
                655,
                453,
                613,
                90,
                814,
                286,
                694,
                96,
                8,
                0,
                750,
                123,
                1050
            ],
            "VerseType": "Numbered"
        },
        {
            "AyahID": 10,
            "RawText": "وَٱلَّذِينَ كَفَرُوا۟ وَكَذَّبُوا۟ بِـَٔايَـٰتِنَآ أُو۟لَـٰٓئِكَ أَصْحَـٰبُ ٱلنَّارِ خَـٰلِدِينَ فِيهَا ۖ وَبِئْسَ ٱلْمَصِيرُ",
            "SanitizedText": "وٱلذين كفروا۟ وكذبوا۟ بـٔايـٰتنآ او۟لـٰٓئك اصحـٰب ٱلنار خـٰلدين فيها ۖ وبئس ٱلمصير",
            "TotalWords": 12,
            "TotalGematricValue": 3969,
            "Words": [
                "وٱلذين",
                "كفروا۟",
                "وكذبوا۟",
                "بـٔايـٰتنآ",
                "او۟لـٰٓئك",
                "اصحـٰب",
                "ٱلنار",
                "خـٰلدين",
                "فيها",
                "ۖ",
                "وبئس",
                "ٱلمصير"
            ],
            "GematricValues": [
                796,
                307,
                735,
                464,
                57,
                101,
                281,
                694,
                96,
                0,
                68,
                370
            ],
            "VerseType": "Numbered"
        },
        {
            "AyahID": 11,
            "RawText": "مَآ أَصَابَ مِن مُّصِيبَةٍ إِلَّا بِإِذْنِ ٱللَّهِ ۗ وَمَن يُؤْمِنۢ بِٱللَّهِ يَهْدِ قَلْبَهُۥ ۚ وَٱللَّهُ بِكُلِّ شَىْءٍ عَلِيمٌ",
            "SanitizedText": "مآ اصاب من مصيبه الا باذن ٱلله ۗ ومن يؤمنۢ بٱلله يهد قلبهۥ ۚ وٱلله بكل شيء عليم",
            "TotalWords": 18,
            "TotalGematricValue": 2224,
            "Words": [
                "مآ",
                "اصاب",
                "من",
                "مصيبه",
                "الا",
                "باذن",
                "ٱلله",
                "ۗ",
                "ومن",
                "يؤمنۢ",
                "بٱلله",
                "يهد",
                "قلبهۥ",
                "ۚ",
                "وٱلله",
                "بكل",
                "شيء",
                "عليم"
            ],
            "GematricValues": [
                41,
                94,
                90,
                147,
                32,
                753,
                65,
                0,
                96,
                100,
                67,
                19,
                137,
                0,
                71,
                52,
                310,
                150
            ],
            "VerseType": "Numbered"
        },
        {
            "AyahID": 12,
            "RawText": "وَأَطِيعُوا۟ ٱللَّهَ وَأَطِيعُوا۟ ٱلرَّسُولَ ۚ فَإِن تَوَلَّيْتُمْ فَإِنَّمَا عَلَىٰ رَسُولِنَا ٱلْبَلَـٰغُ ٱلْمُبِينُ",
            "SanitizedText": "واطيعوا۟ ٱلله واطيعوا۟ ٱلرسول ۚ فان توليتم فانما عليٰ رسولنا ٱلبلـٰغ ٱلمبين",
            "TotalWords": 12,
            "TotalGematricValue": 3437,
            "Words": [
                "واطيعوا۟",
                "ٱلله",
                "واطيعوا۟",
                "ٱلرسول",
                "ۚ",
                "فان",
                "توليتم",
                "فانما",
                "عليٰ",
                "رسولنا",
                "ٱلبلـٰغ",
                "ٱلمبين"
            ],
            "GematricValues": [
                103,
                65,
                103,
                326,
                0,
                131,
                886,
                172,
                110,
                347,
                1062,
                132
            ],
            "VerseType": "Numbered"
        },
        {
            "AyahID": 13,
            "RawText": "ٱللَّهُ لَآ إِلَـٰهَ إِلَّا هُوَ ۚ وَعَلَى ٱللَّهِ فَلْيَتَوَكَّلِ ٱلْمُؤْمِنُونَ",
            "SanitizedText": "ٱلله لآ الـٰه الا هو ۚ وعلي ٱلله فليتوكل ٱلمؤمنون",
            "TotalWords": 10,
            "TotalGematricValue": 1148,
            "Words": [
                "ٱلله",
                "لآ",
                "الـٰه",
                "الا",
                "هو",
                "ۚ",
                "وعلي",
                "ٱلله",
                "فليتوكل",
                "ٱلمؤمنون"
            ],
            "GematricValues": [
                65,
                31,
                36,
                32,
                11,
                0,
                116,
                65,
                576,
                216
            ],
            "VerseType": "Numbered"
        },
        {
            "AyahID": 14,
            "RawText": "يَـٰٓأَيُّهَا ٱلَّذِينَ ءَامَنُوٓا۟ إِنَّ مِنْ أَزْوَٰجِكُمْ وَأَوْلَـٰدِكُمْ عَدُوًّا لَّكُمْ فَٱحْذَرُوهُمْ ۚ وَإِن تَعْفُوا۟ وَتَصْفَحُوا۟ وَتَغْفِرُوا۟ فَإِنَّ ٱللَّهَ غَفُورٌ رَّحِيمٌ",
            "SanitizedText": "يـٰٓايها ٱلذين ءامنوٓا۟ ان من ازوٰجكم واولـٰدكم عدوا لكم فٱحذروهم ۚ وان تعفوا۟ وتصفحوا۟ وتغفروا۟ فان ٱلله غفور رحيم",
            "TotalWords": 19,
            "TotalGematricValue": 7088,
            "Words": [
                "يـٰٓايها",
                "ٱلذين",
                "ءامنوٓا۟",
                "ان",
                "من",
                "ازوٰجكم",
                "واولـٰدكم",
                "عدوا",
                "لكم",
                "فٱحذروهم",
                "ۚ",
                "وان",
                "تعفوا۟",
                "وتصفحوا۟",
                "وتغفروا۟",
                "فان",
                "ٱلله",
                "غفور",
                "رحيم"
            ],
            "GematricValues": [
                27,
                790,
                98,
                51,
                90,
                77,
                107,
                81,
                90,
                1039,
                0,
                57,
                557,
                591,
                1693,
                131,
                65,
                1286,
                258
            ],
            "VerseType": "Numbered"
        },
        {
            "AyahID": 15,
            "RawText": "إِنَّمَآ أَمْوَٰلُكُمْ وَأَوْلَـٰدُكُمْ فِتْنَةٌ ۚ وَٱللَّهُ عِندَهُۥٓ أَجْرٌ عَظِيمٌ",
            "SanitizedText": "انمآ اموٰلكم واولـٰدكم فتنه ۚ وٱلله عندهۥٓ اجر عظيم",
            "TotalWords": 9,
            "TotalGematricValue": 2295,
            "Words": [
                "انمآ",
                "اموٰلكم",
                "واولـٰدكم",
                "فتنه",
                "ۚ",
                "وٱلله",
                "عندهۥٓ",
                "اجر",
                "عظيم"
            ],
            "GematricValues": [
                92,
                137,
                107,
                535,
                0,
                71,
                129,
                204,
                1020
            ],
            "VerseType": "Numbered"
        },
        {
            "AyahID": 16,
            "RawText": "فَٱتَّقُوا۟ ٱللَّهَ مَا ٱسْتَطَعْتُمْ وَٱسْمَعُوا۟ وَأَطِيعُوا۟ وَأَنفِقُوا۟ خَيْرًا لِّأَنفُسِكُمْ ۗ وَمَن يُوقَ شُحَّ نَفْسِهِۦ فَأُو۟لَـٰٓئِكَ هُمُ ٱلْمُفْلِحُونَ",
            "SanitizedText": "فٱتقوا۟ ٱلله ما ٱستطعتم وٱسمعوا۟ واطيعوا۟ وانفقوا۟ خيرا لانفسكم ۗ ومن يوق شح نفسهۦ فاو۟لـٰٓئك هم ٱلمفلحون",
            "TotalWords": 17,
            "TotalGematricValue": 4435,
            "Words": [
                "فٱتقوا۟",
                "ٱلله",
                "ما",
                "ٱستطعتم",
                "وٱسمعوا۟",
                "واطيعوا۟",
                "وانفقوا۟",
                "خيرا",
                "لانفسكم",
                "ۗ",
                "ومن",
                "يوق",
                "شح",
                "نفسهۦ",
                "فاو۟لـٰٓئك",
                "هم",
                "ٱلمفلحون"
            ],
            "GematricValues": [
                587,
                65,
                41,
                979,
                183,
                103,
                244,
                811,
                281,
                0,
                96,
                116,
                308,
                195,
                137,
                45,
                244
            ],
            "VerseType": "Numbered"
        },
        {
            "AyahID": 17,
            "RawText": "إِن تُقْرِضُوا۟ ٱللَّهَ قَرْضًا حَسَنًا يُضَـٰعِفْهُ لَكُمْ وَيَغْفِرْ لَكُمْ ۚ وَٱللَّهُ شَكُورٌ حَلِيمٌ",
            "SanitizedText": "ان تقرضوا۟ ٱلله قرضا حسنا يضـٰعفه لكم ويغفر لكم ۚ وٱلله شكور حليم",
            "TotalWords": 13,
            "TotalGematricValue": 5969,
            "Words": [
                "ان",
                "تقرضوا۟",
                "ٱلله",
                "قرضا",
                "حسنا",
                "يضـٰعفه",
                "لكم",
                "ويغفر",
                "لكم",
                "ۚ",
                "وٱلله",
                "شكور",
                "حليم"
            ],
            "GematricValues": [
                51,
                1507,
                65,
                1101,
                119,
                965,
                90,
                1296,
                90,
                0,
                71,
                526,
                88
            ],
            "VerseType": "Numbered"
        },
        {
            "AyahID": 18,
            "RawText": "عَـٰلِمُ ٱلْغَيْبِ وَٱلشَّهَـٰدَةِ ٱلْعَزِيزُ ٱلْحَكِيمُ",
            "SanitizedText": "عـٰلم ٱلغيب وٱلشهـٰده ٱلعزيز ٱلحكيم",
            "TotalWords": 5,
            "TotalGematricValue": 1764,
            "Words": [
                "عـٰلم",
                "ٱلغيب",
                "وٱلشهـٰده",
                "ٱلعزيز",
                "ٱلحكيم"
            ],
            "GematricValues": [
                140,
                1042,
                350,
                124,
                108
            ],
            "VerseType": "Numbered"
        }
    ]
}